ckanext_dcat_usmetadata-0.6.3-nspkg.pth
ckanext/dcat_usmetadata/__init__.py
ckanext/dcat_usmetadata/blueprint.py
ckanext/dcat_usmetadata/cli.py
ckanext/dcat_usmetadata/db_utils.py
ckanext/dcat_usmetadata/plugin.py
ckanext/dcat_usmetadata/fanstatic/custom.css
ckanext/dcat_usmetadata/fanstatic/webassets.yml
ckanext/dcat_usmetadata/public/index.html
ckanext/dcat_usmetadata/public/manifest.json
ckanext/dcat_usmetadata/public/assets/Bitter-Bold.eot
ckanext/dcat_usmetadata/public/assets/Bitter-Bold.ttf
ckanext/dcat_usmetadata/public/assets/Bitter-Bold.woff
ckanext/dcat_usmetadata/public/assets/Bitter-Bold.woff2
ckanext/dcat_usmetadata/public/assets/Bitter-Italic.eot
ckanext/dcat_usmetadata/public/assets/Bitter-Italic.ttf
ckanext/dcat_usmetadata/public/assets/Bitter-Italic.woff
ckanext/dcat_usmetadata/public/assets/Bitter-Italic.woff2
ckanext/dcat_usmetadata/public/assets/Bitter-Regular.eot
ckanext/dcat_usmetadata/public/assets/Bitter-Regular.ttf
ckanext/dcat_usmetadata/public/assets/Bitter-Regular.woff
ckanext/dcat_usmetadata/public/assets/Bitter-Regular.woff2
ckanext/dcat_usmetadata/public/assets/Latin-Merriweather-Bold.woff2
ckanext/dcat_usmetadata/public/assets/Latin-Merriweather-BoldItalic.woff2
ckanext/dcat_usmetadata/public/assets/Latin-Merriweather-Italic.woff2
ckanext/dcat_usmetadata/public/assets/Latin-Merriweather-Light.woff2
ckanext/dcat_usmetadata/public/assets/Latin-Merriweather-LightItalic.woff2
ckanext/dcat_usmetadata/public/assets/Latin-Merriweather-Regular.woff2
ckanext/dcat_usmetadata/public/assets/OpenSans-Bold-webfont.eot
ckanext/dcat_usmetadata/public/assets/OpenSans-Bold-webfont.ttf
ckanext/dcat_usmetadata/public/assets/OpenSans-Bold-webfont.woff
ckanext/dcat_usmetadata/public/assets/OpenSans-Bold-webfont.woff2
ckanext/dcat_usmetadata/public/assets/OpenSans-Italic-webfont.eot
ckanext/dcat_usmetadata/public/assets/OpenSans-Italic-webfont.ttf
ckanext/dcat_usmetadata/public/assets/OpenSans-Italic-webfont.woff
ckanext_dcat_usmetadata-0.6.3.dist-info/LICENSE
ckanext_dcat_usmetadata-0.6.3.dist-info/METADATA
ckanext_dcat_usmetadata-0.6.3.dist-info/WHEEL
ckanext_dcat_usmetadata-0.6.3.dist-info/entry_points.txt
ckanext_dcat_usmetadata-0.6.3.dist-info/namespace_packages.txt
ckanext_dcat_usmetadata-0.6.3.dist-info/top_level.txt
ckanext_dcat_usmetadata-0.6.3.dist-info/RECORD
