Metadata-Version: 2.1
Name: ckanext-dcat-usmetadata
Version: 0.6.3
Summary: DCAT USMetadata Form App for CKAN
Home-page: https://github.com/GSA/ckanext-dcat_usmetadata
Author: Data.gov
Author-email: datagovhelp@gsa.gov
License: AGPL
Keywords: CKAN
Classifier: Development Status :: 4 - Beta
Classifier: License :: OSI Approved :: GNU Affero General Public License v3 or later (AGPLv3+)
Classifier: Programming Language :: Python :: 3
License-File: LICENSE
